pdm_lev/__init__.py
pdm_lev/command.py
pdm_lev/parser.py
pdm_lev/templates/main.py
pdm_lev/templates/module/__init__.py
pdm_lev/templates/root/.gitignore
pdm_lev/templates/root/.vscode/settings.json
pdm_lev-1.2.7.dist-info/entry_points.txt
pdm_lev-1.2.7.dist-info/WHEEL
pdm_lev-1.2.7.dist-info/METADATA
pdm_lev-1.2.7.dist-info/RECORD
