Metadata-Version: 2.1
Name: pdm-lev
Version: 1.2.7
Author: nihilo
Requires-Python: >=3.7
Requires-Dist: httpx~=0.21
Requires-Dist: msgpack>=1.0.3
